djangocms_highlightjs/__init__.py
djangocms_highlightjs/cms_plugins.py
djangocms_highlightjs/models.py
djangocms_highlightjs/settings.py
djangocms_highlightjs/migrations/0001_initial.py
djangocms_highlightjs/migrations/0002_auto_20160409_1853.py
djangocms_highlightjs/migrations/__init__.py
djangocms_highlightjs/south_migrations/0001_initial.py
djangocms_highlightjs/south_migrations/0002_rename_tables.py
djangocms_highlightjs/south_migrations/__init__.py
djangocms_highlightjs/static/djangocms_highlightjs/img/icon.png
djangocms_highlightjs/static/djangocms_highlightjs/js/highlight.pack.js
djangocms_highlightjs/static/djangocms_highlightjs/themes/arta.css
djangocms_highlightjs/static/djangocms_highlightjs/themes/ascetic.css
djangocms_highlightjs/static/djangocms_highlightjs/themes/atelier-dune.dark.css
djangocms_highlightjs/static/djangocms_highlightjs/themes/atelier-dune.light.css
djangocms_highlightjs/static/djangocms_highlightjs/themes/atelier-forest.dark.css
djangocms_highlightjs/static/djangocms_highlightjs/themes/atelier-forest.light.css
djangocms_highlightjs/static/djangocms_highlightjs/themes/atelier-heath.dark.css
djangocms_highlightjs/static/djangocms_highlightjs/themes/atelier-heath.light.css
djangocms_highlightjs/static/djangocms_highlightjs/themes/atelier-lakeside.dark.css
djangocms_highlightjs/static/djangocms_highlightjs/themes/atelier-lakeside.light.css
djangocms_highlightjs/static/djangocms_highlightjs/themes/atelier-seaside.dark.css
djangocms_highlightjs/static/djangocms_highlightjs/themes/atelier-seaside.light.css
djangocms_highlightjs/static/djangocms_highlightjs/themes/brown_paper.css
djangocms_highlightjs/static/djangocms_highlightjs/themes/brown_papersq.png
djangocms_highlightjs/static/djangocms_highlightjs/themes/dark.css
djangocms_highlightjs/static/djangocms_highlightjs/themes/default.css
djangocms_highlightjs/static/djangocms_highlightjs/themes/docco.css
djangocms_highlightjs-0.5.0.dist-info/DESCRIPTION.rst
djangocms_highlightjs-0.5.0.dist-info/LICENSE.txt
djangocms_highlightjs-0.5.0.dist-info/METADATA
djangocms_highlightjs-0.5.0.dist-info/RECORD
djangocms_highlightjs-0.5.0.dist-info/WHEEL
djangocms_highlightjs-0.5.0.dist-info/metadata.json
djangocms_highlightjs-0.5.0.dist-info/top_level.txt
