Metadata-Version: 2.0
Name: djangocms-highlightjs
Version: 0.5.0
Summary: highlight.js plugin for django CMS 3.0
Home-page: https://github.com/nephila/djangocms-highlightjs
Author: Iacopo Spalletti
Author-email: i.spalletti@nephila.it
License: BSD
Keywords: d,j,a,n,g,o,c,m,s,-,h,i,g,h,l,i,g,h,t,j,s
Platform: UNKNOWN
Classifier: Development Status :: 4 - Beta
Classifier: Framework :: Django
Classifier: Intended Audience :: Developers
Classifier: License :: OSI Approved :: BSD License
Classifier: Natural Language :: English
Classifier: Framework :: Django
Classifier: Framework :: Django :: 1.6
Classifier: Framework :: Django :: 1.7
Classifier: Framework :: Django :: 1.8
Classifier: Framework :: Django :: 1.9
Classifier: Programming Language :: Python :: 2
Classifier: Programming Language :: Python :: 2.6
Classifier: Programming Language :: Python :: 2.7
Classifier: Programming Language :: Python :: 3
Classifier: Programming Language :: Python :: 3.3
Classifier: Programming Language :: Python :: 3.4
Classifier: Programming Language :: Python :: 3.5
Requires-Dist: django-cms (>=3.0)
Requires-Dist: ordereddict
